mameguard/__init__.py
mameguard/cli.py
mameguard/libaudit.py
mameguard/libdat.py
mameguard/libroms.py
mameguard/version.py
mameguard-0.0.6.dist-info/entry_points.txt
mameguard-0.0.6.dist-info/licenses/LICENSE
mameguard-0.0.6.dist-info/WHEEL
mameguard-0.0.6.dist-info/METADATA
mameguard-0.0.6.dist-info/RECORD
