Metadata-Version: 2.4
Name: mameguard
Version: 0.0.6
Summary: A MAME ROM auditing tool
Author-email: Dimitris Zlatanidis <dslackw@gmail.com>
Requires-Python: >=3.9
Classifier: Programming Language :: Python :: 3
Classifier: License :: OSI Approved :: MIT License
Classifier: Operating System :: OS Independent
Classifier: Development Status :: 3 - Alpha
Classifier: Topic :: Games/Entertainment :: Arcade
Classifier: Intended Audience :: End Users/Desktop
Classifier: Natural Language :: English
Classifier: Topic :: Utilities
License-File: LICENSE
Project-URL: Changelog, https://github.com/dslackw/mameguard/blob/main/CHANGELOG.md
Project-URL: Documentation, https://github.com/dslackw/mameguard/blob/main/README.md
Project-URL: Homepage, https://github.com/dslackw/mameguard
Project-URL: Repository, https://github.com/dslackw/mameguard.git
